{
  "project_info": {
    "project_number": "91524812009",
    "firebase_url": "https://flutter-showroom.firebaseio.com",
    "project_id": "flutter-showroom",
    "storage_bucket": "flutter-showroom.appspot.com"
  },
  "client": [
    {
      "client_info": {
        "mobilesdk_app_id": "1:91524812009:android:0e4963c27f658c86",
        "android_client_info": {
          "package_name": "mgm.flutter_catalog"
        }
      },
      "oauth_client": [
        {
          "client_id": "91524812009-nitc6j4pn5ha3aspe2lrmm55b4tov94h.apps.googleusercontent.com",
          "client_type": 3
        }
      ],
      "api_key": [
        {
          "current_key": "AIzaSyCNIw2zwYPeeUO7qf_wug8MQnZ3bZlnwcE"
        }
      ],
      "services": {
        "analytics_service": {
          "status": 1
        },
        "appinvite_service": {
          "status": 1,
          "other_platform_oauth_client": []
        },
        "ads_service": {
          "status": 2
        }
      }
    }
  ],
  "configuration_version": "1"
}